fastapi_token/__init__.py
fastapi_token/acl.py
fastapi_token/encrypt.py
fastapi_token/oauth2.py
fastapi_token/router.py
fastapi_token/schemas.py
fastapi_token_gen-0.3.1.dist-info/METADATA
fastapi_token_gen-0.3.1.dist-info/WHEEL
fastapi_token_gen-0.3.1.dist-info/top_level.txt
fastapi_token_gen-0.3.1.dist-info/RECORD
